{
  "Popular": [
    { "id": 83533, "year": 2025, "title": "Avatar: Fire and Ash", "poster_path": "/g96wHxU7EnoIFwemb2RgohIXrgW.jpg", "backdrop_path": "/iN41Ccw4DctL8npfmYg1j5Tr1eb.jpg" },
    { "id": 1511417, "year": 2025, "title": "Bāhubali: The Epic", "poster_path": "/4sLSorDKKDN944kWngxgQlpdDeg.jpg", "backdrop_path": "/i2GPnSwsdxHtI19e7gZwFVndpqg.jpg" },
    { "id": 1084242, "year": 2025, "title": "Zootopia 2", "poster_path": "/bjUWGw0Ao0qVWxagN3VCwBJHVo6.jpg", "backdrop_path": "/7nfpkR9XsQ1lBNCXSSHxGV7Dkxe.jpg" },
    { "id": 1228246, "year": 2025, "title": "Five Nights at Freddy's 2", "poster_path": "/udAxQEORq2I5wxI97N2TEqdhzBE.jpg", "backdrop_path": "/54BOXpX2ieTXMDzHymdDMnUIzYG.jpg" },
    { "id": 982843, "year": 2025, "title": "The Great Flood", "poster_path": "/1tUOZQDgZaGqZtrB21MieiXARL2.jpg", "backdrop_path": "/6iXTBfCzWKlFCmHxu5oaeZ3an9G.jpg" },
    { "id": 1131759, "year": 2025, "title": "Omniscient Reader: The Prophecy", "poster_path": "/3R3dXO2nm8JyR5NG7SEfii7RzlV.jpg", "backdrop_path": "/fP6L6V42980QmuoyyGXCmWphwpT.jpg" },
    { "id": 1512623, "year": 2025, "title": "Risqué", "poster_path": "/h6OsRrDwbspLnKMvlFl57QFDP7d.jpg", "backdrop_path": "/novE5UrqfLIFEMe5QBnjm18GG4E.jpg" },
    { "id": 1247002, "year": 2025, "title": "The Old Woman with the Knife", "poster_path": "/wbmxnsv41vsg5UEaNDlf203dOWw.jpg", "backdrop_path": "/fepnF3W4VP3s8ui8nDtrlsFVYwO.jpg" },
    { "id": 1439112, "year": 2025, "title": "Muzzle: City of Wolves", "poster_path": "/8qTMRmC07XCGidnKQFLbRM3FoDU.jpg", "backdrop_path": "/ncI1PlBcANixIkgQSnjsSRz4OyT.jpg" },
    { "id": 425274, "year": 2025, "title": "Now You See Me: Now You Don't", "poster_path": "/oD3Eey4e4Z259XLm3eD3WGcoJAh.jpg", "backdrop_path": "/dHSz0tSFuO2CsXJ1CApSauP9Ncl.jpg" },
    { "id": 755898, "year": 2025, "title": "War of the Worlds", "poster_path": "/yvirUYrva23IudARHn3mMGVxWqM.jpg", "backdrop_path": "/iZLqwEwUViJdSkGVjePGhxYzbDb.jpg" },
    { "id": 1137179, "year": 2025, "title": "Yadang: The Snitch", "poster_path": "/y7dsDbG8zVWkrkyOhA6ckZXX1uC.jpg", "backdrop_path": "/9pdoEzieGdUTlRWTAO7QP8q1tIo.jpg" },
    { "id": 1311031, "year": 2025, "title": "Demon Slayer: Kimetsu no Yaiba Infinity Castle", "poster_path": "/fWVSwgjpT2D78VUh6X8UBd2rorW.jpg", "backdrop_path": "/1RgPyOhN4DRs225BGTlHJqCudII.jpg" },
    { "id": 1223601, "year": 2025, "title": "Sisu: Road to Revenge", "poster_path": "/jNsttCWZyPtW66MjhUozBzVsRb7.jpg", "backdrop_path": "/yCatt8lmp3oRFEcOZF8KHhsiASQ.jpg" },
    { "id": 1491902, "year": 2025, "title": "Bang", "poster_path": "/8SUzKOqe2ectvhYdSnR7Vq2F3n1.jpg", "backdrop_path": "/x3s2lEGNguUnQ5YH3Goq7Ud7Lcn.jpg" },
    { "id": 76600, "year": 2022, "title": "Avatar: The Way of Water", "poster_path": "/t6HIqrRAclMCA60NsSmeqe9RmNV.jpg", "backdrop_path": "/cd8YDn7M0lfaHhZdU6MvCDxPalP.jpg" },
    { "id": 1336189, "year": 2025, "title": "Delivery Run", "poster_path": "/eCA5maHDlZtXNTtiLXenwnEw7tc.jpg", "backdrop_path": "/hvut2slhhgJ31UNa9Df7jFfAS0x.jpg" },
    { "id": 1242898, "year": 2025, "title": "Predator: Badlands", "poster_path": "/ef2QSeBkrYhAdfsWGXmp0lvH0T1.jpg", "backdrop_path": "/ebyxeBh56QNXxSJgTnmz7fXAlwk.jpg" },
    { "id": 1419406, "year": 2025, "title": "The Shadow's Edge", "poster_path": "/e0RU6KpdnrqFxDKlI3NOqN8nHL6.jpg", "backdrop_path": "/4BtL2vvEufDXDP4u6xQjjQ1Y2aT.jpg" },
    { "id": 1195518, "year": 2025, "title": "The Unholy Trinity", "poster_path": "/waU3o5qRPNA9bIC59DIsDppll11.jpg", "backdrop_path": "/hyc9gq0Oq5THKak7tB7oqC2Rd6z.jpg" }
  ],

  "Trending": [
    { "id": 83533, "year": 2025, "title": "Avatar: Fire and Ash", "poster_path": "/g96wHxU7EnoIFwemb2RgohIXrgW.jpg", "backdrop_path": "/iN41Ccw4DctL8npfmYg1j5Tr1eb.jpg" },
    { "id": 967941, "year": 2025, "title": "Wicked: For Good", "poster_path": "/u7x3I5V9aP4tMZACmM8ClY8lK6K.jpg", "backdrop_path": "/l8pwO23MCvqYumzozpxynCNfck1.jpg" },
    { "id": 7451, "year": 2002, "title": "xXx", "poster_path": "/xeEw3eLeSFmJgXZzmF2Efww0q3s.jpg", "backdrop_path": "/2OHa6ukEq3Hce7Pc2kvu8wkmMFY.jpg" },
    { "id": 425274, "year": 2025, "title": "Now You See Me: Now You Don't", "poster_path": "/oD3Eey4e4Z259XLm3eD3WGcoJAh.jpg", "backdrop_path": "/dHSz0tSFuO2CsXJ1CApSauP9Ncl.jpg" },
    { "id": 106379, "year": 2024, "title": "Fallout", "poster_path": "/c15BtJxCXMrISLVmysdsnZUPQft.jpg", "backdrop_path": "/cIgHBLTMbcIkS0yvIrUUVVKLdOz.jpg" },
    { "id": 1234731, "year": 2025, "title": "Anaconda", "poster_path": "/5MDnvvkOqthhE5gQebzkcOhD1p5.jpg", "backdrop_path": "/yo41R39airbREp0PYfG30Ofxtgt.jpg" },
    { "id": 225171, "year": 2025, "title": "Pluribus", "poster_path": "/nrM2xFUfKJJEmZzd5d7kohT2G0C.jpg", "backdrop_path": "/vNCNUxNHHgP0WsA19hxztUsG3yG.jpg" },
    { "id": 200875, "year": 2025, "title": "IT: Welcome to Derry", "poster_path": "/nyy3BITeIjviv6PFIXtqvc8i6xi.jpg", "backdrop_path": "/2fOKVDoc2O3eZmBZesWPuE5kgPN.jpg" },
    { "id": 1214931, "year": 2025, "title": "Nuremberg", "poster_path": "/sxu8TsG7k06ymWL98ELEIE1EMZV.jpg", "backdrop_path": "/ajzEWXl1z75Mx6lOj9lToHt5t6Z.jpg" },
    { "id": 1259102, "year": 2025, "title": "Eternity", "poster_path": "/o8pg20G67BGmQvRkXwstNre062J.jpg", "backdrop_path": "/fuacZLpnohQtLD0AhtCErcPVL98.jpg" },
    { "id": 812583, "year": 2025, "title": "Wake Up Dead Man: A Knives Out Mystery", "poster_path": "/eDKPKlMtHjRQimYQz4eOgKYW5q6.jpg", "backdrop_path": "/fiRDzpcJe7qz3yIR43hdXIE3NHv.jpg" }
 ],

  "Horror": [
    { "id": 1091, "year": 1982, "title": "The Thing", "poster_path": "/a9RjXOIIB56k2rGoL3Fk3nRHHHQ.jpg", "backdrop_path": "/jaO8WurWoUBE55nskqtFqPZFFaO.jpg" },
    { "id": 539, "year": 1960, "title": "Psycho", "poster_path": "/yz4QVqPx3h1hD1DfqqQkCq3rmxW.jpg", "backdrop_path": "/uif5fUshJrXyyDzfpzp1DLw3N0S.jpg" },
    { "id": 6114, "year": 1992, "title": "Bram Stoker's Dracula", "poster_path": "/n39glC4GkBeCbwdenES8ZBodim8.jpg", "backdrop_path": "" },
    { "id": 348, "year": 1979, "title": "Alien", "poster_path": "/vfrQk5IPloGg1v9Rzbh2Eg3VGyM.jpg", "backdrop_path": "/hdHIjZxq3SWFqpAz4NFhdbud0iz.jpg" },
    { "id": 420634, "year": 2018, "title": "Terrifier", "poster_path": "/fjXqhGmaeQpB73WerhrYU6HlyV5.jpg", "backdrop_path": "" },
    { "id": 609, "year": 1982, "title": "Poltergeist", "poster_path": "/m5AKo8iZAYulI87Uzxkn87vRY07.jpg", "backdrop_path": "" },
    { "id": 493922, "year": 2018, "title": "Hereditary", "poster_path": "/hjlZSXM86wJrfCv5VKfR5DI2VeU.jpg", "backdrop_path": "" },
    { "id": 138843, "year": 2013, "title": "The Conjuring", "poster_path": "/wVYREutTvI2tmxr6ujrHT704wGF.jpg", "backdrop_path": "" },
    { "id": 2654, "year": 1994, "title": "In the Mouth of Madness", "poster_path": "/msh4tEUzbnEqlHcFOUH4O0Zti8r.jpg", "backdrop_path": "" },
    { "id": 170, "year": 2002, "title": "28 Days Later", "poster_path":"/sQckQRt17VaWbo39GIu0TMOiszq.jpg", "backdrop_path": "" },
    { "id": 396535, "year": 2016, "title": "Train to Busan", "poster_path":"/vNVFt6dtcqnI7hqa6LFBUibuFiw.jpg", "backdrop_path": "" },
    { "id": 14836, "year": 2009, "title": "Coraline", "poster_path":"/4jeFXQYytChdZYE9JYO7Un87IlW.jpg", "backdrop_path": "" },
    { "id": 694, "year": 1980, "title": "The Shining", "poster_path": "/xazWoLealQwEgqZ89MLZklLZD3k.jpg", "backdrop_path": "/mmd1HnuvAzFc4iuVJcnBrhDNEKr.jpg" },
    { "id": 948, "year": 1978, "title": "Halloween", "poster_path": "/wijlZ3HaYMvlDTPqJoTCWKFkCPU.jpg", "backdrop_path": "" },
    { "id": 242224, "year": 2014, "title": "The Babadook", "poster_path": "/qt3fqapeo94TfvMyld8P7gkpXLz.jpg", "backdrop_path": "" },
    { "id": 419430, "year": 2017, "title": "Get Out", "poster_path": "/tFXcEccSQMf3lfhfXKSU9iRBpa3.jpg", "backdrop_path": "" },
    { "id": 76617, "year": 1974, "title": "Texas Chainsaw 3D", "poster_path": "/qaPvvHP1kKlQaUAXQZQAWitqBOT.jpg", "backdrop_path": "" },
    { "id": 2671, "year": 1998, "title": "Ring", "poster_path": "/1YINof6kN5yRdePEbcU5360ejoq.jpg", "backdrop_path": "" },
    { "id": 713704, "year": 2023, "title": "Evil Dead Rise", "poster_path": "/5ik4ATKmNtmJU6AYD0bLm56BCVM.jpg", "backdrop_path": "" },
    { "id": 2004, "year": 2004, "title": "Saw", "poster_path": "/rLNSOudrayDBo1uqXjrhxcjODIC.jpg", "backdrop_path": "" },
    { "id": 9552, "year": 1973, "title": "The Exorcist", "poster_path": "/5x0CeVHJI8tcDx8tUUwYHQSNILq.jpg", "backdrop_path": "" }
  ],
 
  "Vintage":[
    { "id": 653, "year": 1922, "title": "Nosferatu", "poster_path": "/zv7J85D8CC9qYagAEhPM63CIG6j.jpg"},
    { "id": 15, "year": 1941, "title": "Citizen Kane", "poster_path": "/sav0jxhqiH0bPr2vZFU0Kjt2nZL.jpg"},
    { "id": 1939, "year": 1944, "title": "Laura", "poster_path": "/j0zEiFFrdbZnMXqD3piOtZBJeNB.jpg"},
    { "id": 1480, "year": 1958, "title": "Touch of Evil", "poster_path": "/1pvRgmfBaoMczIJBOi9gCOZ4FMC.jpg"},
    { "id": 3035, "year": 1931, "title": "Frankenstein", "poster_path": "/mu6wHwH0IwCCaEYtpqujuPJYat1.jpg"},
    { "id": 138, "year": 1931, "title": "Dracula", "poster_path": "/ueVSPt7vAba0XScHWTDWS5tNxYX.jpg"},
    { "id": 964, "year": 1925, "title": "The Phantom of the Opera", "poster_path": "/mvaYpAYj957C2tlq3vVJPSzGJXK.jpg"},
    { "id": 18987, "year": 1923, "title": "The Hunchback of Notre Dame", "poster_path": "/3oheTQrTuqS1jPUW6GOc65ZbM5u.jpg"},
    { "id": 19, "year": 1927, "title": "Metropolis", "poster_path": "/vZIJxGnjcswPCAa52jhbl01FQkV.jpg"},
    { "id": 234, "year": 1920, "title": "The Cabinet of Dr. Caligari", "poster_path": "/myK9DeIsXWGKgUTZyGXg2IfFk0W.jpg"},
    { "id": 30982, "year": 1915, "title": "The Tramp", "poster_path": "/v36MPfeBlhUBgVXu7jBofZorrbM.jpg"},
    { "id": 10098, "year": 1921, "title": "The Kid", "poster_path": "/A9NWYyn7eX0H9XIjaOvfWJ9mCGA.jpg"},
    { "id": 828, "year": 1951, "title": "The Day the Earth Stood Still", "poster_path": "/eslDNzf0LF1m9GsgUXlmyfTcC6Y.jpg"},
    { "id": 548, "year": 1950, "title": "Rashomon", "poster_path": "/vL7Xw04nFMHwnvXRFCmYYAzMUvY.jpg"},
    { "id": 11878, "year": 1961, "title": "Yojimbo", "poster_path": "/tN7kYPjRhDolpui9sc9Eq9n5b2O.jpg"},
    { "id": 962, "year": 1925, "title": "The Gold Rush", "poster_path": "/eQRFo1qwRREYwj47Yoe1PisgOle.jpg"},
    { "id": 27517, "year": 1928, "title": "The Man Who Laughs", "poster_path": "/iQXBMr4NzQst4X0rDU6MII6ZUOM.jpg"},
    { "id": 2760, "year": 1927, "title": "The Lodger", "poster_path": "/tD84zwFeFRf3zG98x558N3PBMV.jpg"},
    { "id": 289, "year": 1943, "title": "Casablanca", "poster_path": "/oyGRZVIthHJjc98ekKpeWpDh8Ws.jpg"},
    { "id": 770, "year": 1939, "title": "Gone with the Wind", "poster_path": "/lNz2Ow0wGCAvzckW7EOjE03KcYv.jpg"}
  ],

  "Comedy": [
    { "id": 1035259, "year": 2025, "title": "Naked Gun", "poster_path": "/rmwQ8GsdQ1M3LtemNWLErle2nBU.jpg", "backdrop_path": "/images/poster.jpg" },
    { "id": 680, "year": 1994, "title": "Pulp Fiction", "poster_path": "/vQWk5YBFWF4bZaofAbv0tShwBvQ.jpg", "backdrop_path": "/images/poster.jpg" },
    { "id": 816, "year": 1997, "title": "Austin Powers: International Man of Mystery", "poster_path": "/5uD4dxNX8JKFjWKYMHyOsqhi5pN.jpg", "backdrop_path": "/images/poster.jpg" },
    { "id": 9486, "year": 2003, "title": "Johnny English", "poster_path": "/mmzW88tnkB2MnOV3Un2F9IUxSnZ.jpg", "backdrop_path": "/images/poster.jpg" },
    { "id": 9470, "year": 2004, "title": "Kung Fu Hustle", "poster_path": "/exbyTbrvRUDKN2mcNEuVor4VFQW.jpg", "backdrop_path": "/images/poster.jpg" },
    { "id": 2109, "year": 1998, "title": "Rush Hour", "poster_path": "/we7wOLVFgxhzLzUt0qNe50xdIQZ.jpg", "backdrop_path": "/images/poster.jpg" },
    { "id": 9502, "year": 2008, "title": "Kung Fu Panda", "poster_path": "/wWt4JYXTg5Wr3xBW2phBrMKgp3x.jpg", "backdrop_path": "/images/poster.jpg" },
    { "id": 194, "year": 2001, "title": "Amelie", "poster_path": "/nSxDa3M9aMvGVLoItzWTepQ5h5d.jpg", "backdrop_path": "/images/poster.jpg" },
    { "id": 76493, "year": 2012, "title": "The Dictator", "poster_path": "/n0W7kajF4GFMRk2c0wWwMQqTaDM.jpg", "backdrop_path": "/images/poster.jpg" },
    { "id": 935, "year": 1964, "title": "Dr. Strangelove or: How I Learned to Stop Worrying and Love the Bomb", "poster_path": "/7SixLzxcqezkZEYU8pcHZgbkmjp.jpg", "backdrop_path": "/images/poster.jpg" },
    { "id": 18785, "year": 2009, "title": "The Hangover", "poster_path": "/A0uS9rHR56FeBtpjVki16M5xxSW.jpg", "backdrop_path": "" },
    { "id": 284053, "year": 2017, "title": "Thor: Ragnarok", "poster_path": "/rzRwTcFvttcN1ZpX2xv4j3tSdJu.jpg", "backdrop_path": "" },
    { "id": 4247, "year": 2000, "title": "Scary Movie", "poster_path": "/fVQFPRuw3yWXojYDJvA5EoFjUOY.jpg", "backdrop_path": "" },
    { "id": 44896, "year": 2011, "title": "Rango", "poster_path": "/A5MP1guV8pbruieG0tnpPIbaJtt.jpg", "backdrop_path": "" },
    { "id": 207703, "year": 2014, "title": "Kingsman: The Secret Service", "poster_path": "/r6q9wZK5a2K51KFj4LWVID6Ja1r.jpg", "backdrop_path": "" },
    { "id": 19908, "year": 2009, "title": "Zombieland", "poster_path": "/dUkAmAyPVqubSBNRjRqCgHggZcK.jpg", "backdrop_path": "" },
    { "id": 607, "year": 1997, "title": "Men in Black", "poster_path": "h/uLOmOF5IzWoyrgIF5MfUnh5pa1X.jpg", "backdrop_path": "" },
    { "id": 170657, "year": 2013, "title": "Journey to the West: Conquering the Demons", "poster_path": "/XcFMQQfx1gMlh1RyEednP6frNC.jpg", "backdrop_path": "" },
    { "id": 914, "year": 1940, "title": "The Great Dictator", "poster_path": "/nhMXB8GTdswYMCL9nepDZymJCOr.jpg", "backdrop_path": "/images/poster.jpg" },
    { "id": 18610, "year": 2008, "title": "One Two Three", "poster_path": "/8NZvA9tT1eHAL3fSM10cnWFX9JL.jpg", "backdrop_path": "/images/poster.jpg" },
    { "id": 19670, "year": 2006, "title": "Golmaal: Fun Unlimited", "poster_path": "/3ubefqLk26Gy0lXCfGIu8hQrBak.jpg", "backdrop_path": "/images/poster.jpg" }
  ],

  "Action": [
    { "id": 155,     "year": 2008, "title": "The Dark Knight",                              "poster_path": "/qJ2tW6WMUDux911r6m7haRef0WH.jpg", "backdrop_path": "/enNubozHn9pXi0ycTVYUWfpHZm.jpg" },
    { "id": 122,     "year": 2003, "title": "The Lord of the Rings: The Return of the King","poster_path": "/rCzpDGLbOoPwLjy3OAm5NUPOTrC.jpg", "backdrop_path": "/2u7zbn8EudG6kLlBzUYqP8RyFU4.jpg" },
    { "id": 346,     "year": 1954, "title": "Seven Samurai",                                "poster_path": "/8OKmBV5BUFzmozIC3pPWKHy17kx.jpg", "backdrop_path": "/sJNNMCc6B7KZIY3LH3JMYJJNH5j.jpg" },
    { "id": 76341,   "year": 2015, "title": "Mad Max: Fury Road",                           "poster_path": "/hA2ple9q4qnwxp3hKVNhroipsir.jpg", "backdrop_path": "" },
    { "id": 9495,    "year": 1994, "title": "The Crow",                                     "poster_path": "/rMMB3v6jYHjsvXRNJYESacoTD7j.jpg", "backdrop_path": "" },
    { "id": 24,      "year": 2003, "title": "Kill Bill: Vol. 1",                            "poster_path": "/v7TaX8kXMXs5yFFGR41guUDNcnB.jpg", "backdrop_path": "" },
    { "id": 187,     "year": 2005, "title": "Sin City",                                     "poster_path": "/i66G50wATMmPrvpP95f0XP6ZdVS.jpg", "backdrop_path": "" },
    { "id": 39254,   "year": 2011, "title": "Real Steel",                                   "poster_path": "/4GIeI5K5YdDUkR3mNQBoScpSFEf.jpg", "backdrop_path": "" },
    { "id": 98,      "year": 1976, "title": "Gladiator",                                    "poster_path": "/ty8TGRuvJLPUmAR1H1nRIsgwvim.jpg", "backdrop_path": "" },
    { "id": 1368,    "year": 1982, "title": "First Blood",                                  "poster_path": "/a9sa6ERZCpplbPEO7OMWE763CLD.jpg", "backdrop_path": "" },
    { "id": 1271,    "year": 2006, "title": "300",                                          "poster_path": "/h7Lcio0c9ohxPhSZg42eTlKIVVY.jpg", "backdrop_path": "" },
    { "id": 245891,  "year": 2014, "title": "John Wick",                                    "poster_path": "/fZPSd91yGE9fCcCe6OoQr6E3Bev.jpg", "backdrop_path": "" },
    { "id": 670,     "year": 2003, "title": "Oldboy",                                       "poster_path": "/pWDtjs568ZfOTMbURQBYuT4Qxka.jpg", "backdrop_path": "" },
    { "id": 100402,  "year": 2014, "title": "Captain America: The Winter Soldier",          "poster_path": "/tVFRpFw3xTedgPGqxW0AOI8Qhh0.jpg", "backdrop_path": "" },
    { "id": 14711,   "year": 2009, "title": "Afro Samurai: Resurrection",                   "poster_path": "/6snrLj3Ydmbu5L9giAYtiSNwE0U.jpg", "backdrop_path": "" },
    { "id": 106,     "year": 1987, "title": "Predator",                                     "poster_path": "/k3mW4qfJo6SKqe6laRyNGnbB9n5.jpg", "backdrop_path": "" },
    { "id": 9387,    "year": 2011, "title": "Conan the Barbarian",                          "poster_path": "/qw2A587Ee61IwcSOLNFRhuOACZZ.jpg", "backdrop_path": "" },
    { "id": 603,     "year": 1999, "title": "The Matrix",                                   "poster_path": "/p96dm7sCMn4VYAStA6siNz30G1r.jpg", "backdrop_path": "" },
    { "id": 218,     "year": 1984, "title": "The Terminator",                               "poster_path": "/hzXSE66v6KthZ8nPoLZmsi2G05j.jpg", "backdrop_path": "" },
    { "id": 11230,   "year": 1978, "title": "Drunken Master",                               "poster_path": "/cf43J2SH8tECZVl9N5n0Q6Ckche.jpg", "backdrop_path": "" },
    { "id": 9461,    "year": 1973, "title": "Enter the Dragon",                             "poster_path": "/fyrh2ULEcmLpGTVLPQqFW45hqr5.jpg", "backdrop_path": "" },
    { "id": 1891,    "year": 2005, "title": "Star Wars: Episode III – Revenge of the Sith", "poster_path": "/nNAeTmF4CtdSgMDplXTDPOpYzsX.jpg", "backdrop_path": "" }
  ]
}